embedbase_qdrant/__init__.py
embedbase_qdrant/qdrant_db.py
embedbase_qdrant-1.0.1.dist-info/METADATA
embedbase_qdrant-1.0.1.dist-info/WHEEL
embedbase_qdrant-1.0.1.dist-info/RECORD
